fastfp/__init__.py
fastfp/constants.py
fastfp/fastfp.py
fastfp/nmfp.py
fastfp/utils.py
fastfp-0.1.0.dist-info/licenses/LICENSE
fastfp-0.1.0.dist-info/WHEEL
fastfp-0.1.0.dist-info/METADATA
fastfp-0.1.0.dist-info/RECORD
