Metadata-Version: 2.4
Name: fastfp
Version: 0.1.0
Summary: JAX implementation of pulsar timing Fp-statistic
Author-email: Gabe Freedman <freedma5@uwm.edu>
Requires-Python: >=3.9
Classifier: Programming Language :: Python :: 3
Classifier: License :: OSI Approved :: MIT License
License-File: LICENSE
Requires-Dist: jax[cpu]
Requires-Dist: jaxlib
Requires-Dist: enterprise-pulsar
Requires-Dist: enterprise_extensions
Requires-Dist: tqdm
Requires-Dist: black ; extra == "dev"
Requires-Dist: flake8 ; extra == "dev"
Requires-Dist: flake8-pyprojecttoml ; extra == "dev"
Requires-Dist: jax[cuda12] ; extra == "gpu"
Provides-Extra: dev
Provides-Extra: gpu
